franklinwh/__init__.py
franklinwh/api.py
franklinwh/caching_thread.py
franklinwh/caching_thread_test.py
franklinwh/client.py
franklinwh-1.0.0.dist-info/METADATA
franklinwh-1.0.0.dist-info/WHEEL
franklinwh-1.0.0.dist-info/licenses/LICENSE
franklinwh-1.0.0.dist-info/RECORD
