Metadata-Version: 2.4
Name: franklinwh
Version: 1.0.0
Summary: Python wrapper for FranklinWH
Project-URL: Homepage, https://github.com/richo/franklinwh-python
Project-URL: Issues, https://github.com/richo/franklinwh-python/issues
Author-email: Richo Butts <richo@psych0tik.net>
License-File: LICENSE
Requires-Python: >=3.8
Requires-Dist: httpx[http2]>=0.28.1
Provides-Extra: bin
Requires-Dist: jsonpickle; extra == 'bin'
Provides-Extra: build
Requires-Dist: build; extra == 'build'
Requires-Dist: twine; extra == 'build'
Provides-Extra: test
Requires-Dist: pytest; extra == 'test'
